[
    {
        "title": "How to create a good problem solving interview",
        "localSlug": "how-to-create-a-good-problem-solving-interview",
        "originalUrl": "https://blog.dashlane.com/how-to-create-a-good-problem-solving-interview/",
        "description": "First part of an article I've wrote for Dashlane engineering blog"
    },
    {
        "title": "Becoming a good technical interviewer",
        "localSlug": "becoming-a-good-technical-interviewer",
        "originalUrl": "https://blog.dashlane.com/becoming-a-good-technical-interviewer/",
        "description": "Second part of an article I've wrote for Dashlane engineering blog"
    }
]
